acumenindexer/__init__.py
acumenindexer/main.py
acumenindexer-0.0.1.dist-info/METADATA
acumenindexer-0.0.1.dist-info/WHEEL
acumenindexer-0.0.1.dist-info/licenses/LICENSE
acumenindexer-0.0.1.dist-info/RECORD
