Metadata-Version: 2.3
Name: acumenindexer
Version: 0.0.1
Summary: The AcumenIndexer
Project-URL: Homepage, https://github.com/cosmaadrian/acumen-indexer
Project-URL: Issues, https://github.com/cosmaadrian/acumen-indexer/issues
Author-email: Adrian Cosma <cosma.i.adrian@gmail.com>
License-File: LICENSE
Classifier: License :: OSI Approved :: MIT License
Classifier: Operating System :: OS Independent
Classifier: Programming Language :: Python :: 3
Requires-Python: >=3.8
